pyserved/__init__.py
pyserved/pdhost.py
pyserved/pdlisten.py
pyserved/pdsnd.py
pyserved/bin/pdhost
pyserved/bin/pdlisten
pyserved/bin/pdsnd
pyserved-2.1.data/scripts/pdhost
pyserved-2.1.data/scripts/pdlisten
pyserved-2.1.data/scripts/pdsnd
pyserved-2.1.dist-info/LICENSE.txt
pyserved-2.1.dist-info/METADATA
pyserved-2.1.dist-info/WHEEL
pyserved-2.1.dist-info/top_level.txt
pyserved-2.1.dist-info/RECORD
