Metadata-Version: 2.1
Name: pyserved
Version: 2.1
Summary: Network transfer/hosting utilities by SblipDev.
Home-page: https://github.com/SblipDev/pyserved/
Author: Shaurya Pratap Singh
Author-email: shaurya.p.singh21@gmail.com
License: MIT
Platform: UNKNOWN
License-File: LICENSE.txt
Requires-Dist: rich
Requires-Dist: choam
